packaging_demo/__init__.py
packaging_demo/logic.py
packaging_demo/main.py
packaging_demo-0.0.1.dist-info/METADATA
packaging_demo-0.0.1.dist-info/WHEEL
packaging_demo-0.0.1.dist-info/entry_points.txt
packaging_demo-0.0.1.dist-info/top_level.txt
packaging_demo-0.0.1.dist-info/RECORD
