Metadata-Version: 2.1
Name: packaging_demo
Version: 0.0.1
Summary: An application that informs you of the time in different locations and timezones
Author: haddad skander
Author-email: skander.haddad.perso@gmail.com
Classifier: Programming Language :: Python :: 3
Classifier: License :: OSI Approved :: MIT License
Classifier: Operating System :: OS Independent
Requires-Dist: click
Requires-Dist: pytz
